{
  "total" : 1,
  "suite_elapsed_s" : 0.03,
  "git_branch" : "ethereum",
  "git_sha" : "31ba27b",
  "python_version" : "3.12.10",
  "run_at" : "2026-04-15T17:40:32Z",
  "summary" : {
    "disputes_triggered" : 4,
    "reverts" : 0,
    "total_transactions" : 10,
    "resolutions_executed" : 2,
    "attack_attempts" : 0,
    "total_volume" : 2000,
    "pending_settlements_executed" : 0,
    "invariant_violations" : 0,
    "attack_successes" : 0,
    "total_escrows" : 4
  },
  "scenarios" : [ {
    "name" : "S33  f10-cascade-escalation-drain",
    "ok" : true,
    "elapsed" : 0.03,
    "steps" : 10,
    "outcome" : "pass",
    "halt_reason" : null,
    "metrics" : {
      "disputes_triggered" : 4,
      "reverts" : 0,
      "resolutions_executed" : 2,
      "attack_attempts" : 0,
      "total_volume" : 2000,
      "pending_settlements_executed" : 0,
      "invariant_violations" : 0,
      "attack_successes" : 0,
      "total_escrows" : 4
    }
  } ],
  "passed" : 1
}